[
    {
        "bookId": 1,
        "bookName": "মেঘের উপর তারা",
        "author": "হুমায়ূন আহমেদ",
        "image": "https://i.ibb.co/XD25pC7/book.jpg",
        "review": "একটি চমৎকার অসাধারণ গল্প, যা প্রেম ও পরিবারের সঙ্গে সংযুক্ত।",
        "totalPages": 320,
        "rating": 4.8,
        "category": "প্রেম",
        "tags": [
            "জীবনযাত্রা",
            "বিপ্লব"
        ],
        "publisher": "আনন্দ পাবলিশার্স",
        "yearOfPublishing": 1976
    },
    {
        "bookId": 2,
        "bookName": "হুমায়ুন আহমেদের সমগ্র",
        "author": "হুমায়ূন আহমেদ",
        "image": "https://i.ibb.co/XD25pC7/book.jpg",
        "review": "বাংলাদেশী সাহিত্যে একজন অদম্য লেখক যিনি অনেক প্রশংসিত।",
        "totalPages": 800,
        "rating": 4.9,
        "category": "প্রেম",
        "tags": [
            "হাসির গল্প",
            "ভৌতিক"
        ],
        "publisher": "আনন্দ পাবলিশার্স",
        "yearOfPublishing": 1980
    },
    {
        "bookId": 3,
        "bookName": "ফেলুদা সমগ্র",
        "author": "সাত্যজিত রায়",
        "image": "https://i.ibb.co/XD25pC7/book.jpg",
        "review": "ফেলুদা গল্পের এই সমগ্র তুলে ধরে আমরা ফেলুদার অসামান্য মজার ও মিষ্টি দুনিয়ায়।",
        "totalPages": 400,
        "rating": 4.7,
        "category": "প্রেম",
        "tags": [
            "মিস্টারি",
            "সাসপেন্স"
        ],
        "publisher": "আনন্দ পাবলিশার্স",
        "yearOfPublishing": 1972
    },
    {
        "bookId": 4,
        "bookName": "শেষের কবিতা",
        "author": "রবীন্দ্রনাথ ঠাকুর",
        "image": "https://i.ibb.co/XD25pC7/book.jpg",
        "review": "একটি সুন্দর প্রেমের গল্প, যেখানে সমাজের আদর্শ, বিশ্বাস এবং সম্পর্কের বিভিন্ন দৃষ্টিভঙ্গি উপস্থাপন করা হয়েছে।",
        "totalPages": 250,
        "rating": 4.6,
        "category": "প্রেম",
        "tags": [
            "সাহিত্য",
            "পরিবার"
        ],
        "publisher": "বিশ্ববিদ্যালয় প্রকাশনী",
        "yearOfPublishing": 1929
    },
    {
        "bookId": 5,
        "bookName": "দুর্গা সমগ্র",
        "author": "বঙ্কিমচন্দ্র চট্টোপাধ্যায়",
        "image": "https://i.ibb.co/XD25pC7/book.jpg",
        "review": "একটি ঐতিহাসিক উপন্যাস, যা বিশ্ববিদ্যালয়ের ছাত্র-ছাত্রীদের বিরুদ্ধে স্বাধীনতা সংগ্রাম প্রণয়নের সময়ের ঘটনার চিত্রণ করে।",
        "totalPages": 400,
        "rating": 4.7,
        "category": "ঐতিহাসিক",
        "tags": [
            "স্বাধীনতা",
            "বিদ্রোহ"
        ],
        "publisher": "সমাজ প্রকাশন",
        "yearOfPublishing": 1875
    },
    {
        "bookId": 6,
        "bookName": "পথের পাঁচালী",
        "author": "বিভূতিভূষণ বন্দ্যোপাধ্যায়",
        "image": "https://i.ibb.co/XD25pC7/book.jpg",
        "review": "একটি চিরন্তন বাংলা উপন্যাস, যা ছোটদের জীবনের অনুভব ও স্বপ্ন উল্লেখ করে।",
        "totalPages": 250,
        "rating": 4.5,
        "category": "সাহিত্য",
        "tags": [
            "পরিবার",
            "শিশুসাহিত্য"
        ],
        "publisher": "আনন্দ পাবলিশার্স",
        "yearOfPublishing": 1929
    },
    {
        "bookId": 7,
        "bookName": "মেঘের ওপারে তিন আকাশ",
        "author": "হুমায়ূন আহমেদ",
        "image": "https://i.ibb.co/XD25pC7/book.jpg",
        "review": "একটি অসাধারণ প্রেমের গল্প, যা বিভিন্ন ধর্ম, সংস্কৃতি এবং অভিজাত প্রতিবন্ধীদের মধ্যে প্রেম ও ভালোবাসার অভিজ্ঞতা উপস্থাপন করে।",
        "totalPages": 270,
        "rating": 4.6,
        "category": "প্রেম",
        "tags": [
            "ভালোবাসা",
            "বিপ্লব"
        ],
        "publisher": "আনন্দ পাবলিশার্স",
        "yearOfPublishing": 1990
    },
    {
        "bookId": 8,
        "bookName": "ঘাম ও মেঘ",
        "author": "তাহমিনা আনমোল",
        "image": "https://i.ibb.co/XD25pC7/book.jpg",
        "review": "একটি চিরন্তন বাংলা উপন্যাস, যা একটি মেয়ের জীবনের প্রতিটি অংশ উল্লেখ করে এবং তার সমস্যাগুলির সামনে যে পরিহারগুলি রয়েছে তা উল্লেখ করে।",
        "totalPages": 320,
        "rating": 4.7,
        "category": "সাহিত্য",
        "tags": [
            "বাঙালি",
            "মেয়ে"
        ],
        "publisher": "আনন্দ পাবলিশার্স",
        "yearOfPublishing": 2015
    },
    {
        "bookId": 9,
        "bookName": "আরও একটি পিন্যাকেল চশমা",
        "author": "হুমায়ূন আহমেদ",
        "image": "https://i.ibb.co/XD25pC7/book.jpg",
        "review": "একটি বিনোদনমূলক গল্প, যা দেশ ও বিদেশে আত্মপ্রকাশ এবং বিভিন্ন সমাজের মানুষের সাথে তাদের সম্পর্কে প্রকাশ করে।",
        "totalPages": 250,
        "rating": 4.5,
        "category": "বিনোদন",
        "tags": [
            "হাসির গল্প",
            "জীবনী"
        ],
        "publisher": "আনন্দ পাবলিশার্স",
        "yearOfPublishing": 1985
    },
    {
        "bookId": 10,
        "bookName": "আমার ভিতরে বাস্তবের সৃষ্টি",
        "author": "জাহানারা ইমাম",
        "image": "https://i.ibb.co/XD25pC7/book.jpg",
        "review": "একটি মনোযোগ দর্শানোর উপন্যাস, যেখানে লেখিকা তার অভিজ্ঞতা, মতামত, ভাবনা এবং ধারণাগুলি নিয়ে আলোচনা করেন।",
        "totalPages": 200,
        "rating": 4.8,
        "category": "বিচার",
        "tags": [
            "স্বপ্ন",
            "মনোযোগ"
        ],
        "publisher": "প্রথমা পাবলিশার্স",
        "yearOfPublishing": 2010
    },
    {
        "bookId": 11,
        "bookName": "সাত রং জাহাজ",
        "author": "তাহমিনা আনমোল",
        "image": "https://i.ibb.co/XD25pC7/book.jpg",
        "review": "একটি চমৎকার প্রেমের গল্প, যেখানে পুরুষ এবং নারীর মধ্যে প্রেম এবং ভালোবাসার অভিজ্ঞতা উল্লেখ করা হয়েছে।",
        "totalPages": 280,
        "rating": 4.7,
        "category": "প্রেম",
        "tags": [
            "পরিবার",
            "প্রয়াত"
        ],
        "publisher": "আনন্দ পাবলিশার্স",
        "yearOfPublishing": 2005
    },
    {
        "bookId": 12,
        "bookName": "সেই সব সময়",
        "author": "জাহানারা ইমাম",
        "image": "https://i.ibb.co/XD25pC7/book.jpg",
        "review": "একটি জীবনযাপনের ব্যবস্থা, যেখানে লেখিকা তার প্রিয়জনদের সাথে কৈশোর থেকে বৃদ্ধাবস্থায় তাদের সম্পর্ক নিয়ে আলোচনা করেন।",
        "totalPages": 320,
        "rating": 4.6,
        "category": "স্মৃতি",
        "tags": [
            "বন্ধুত্ব",
            "সম্পর্ক"
        ],
        "publisher": "প্রথমা পাবলিশার্স",
        "yearOfPublishing": 2013
    }
]